kofe_mcp_server/__init__.py
kofe_mcp_server/config.yaml
kofe_mcp_server/server.py
kofe_mcp_server-0.1.2.dist-info/METADATA
kofe_mcp_server-0.1.2.dist-info/WHEEL
kofe_mcp_server-0.1.2.dist-info/entry_points.txt
kofe_mcp_server-0.1.2.dist-info/RECORD
