Metadata-Version: 2.4
Name: kofe-mcp-server
Version: 0.1.2
Summary: kofe tools
Author-email: zhendongchen <zhendongchen@emotibot.com>
Requires-Python: >=3.12
Requires-Dist: mcp>=1.4.1
Requires-Dist: omegaconf>=2.3.0
Requires-Dist: requests>=2.32.3
